cloudrift-0.46.3.dist-info/licenses/LICENSE
rift/__init__.py
rift/client/__init__.py
rift/client/client.py
rift/client/internal.py
rift/client/public.py
cloudrift-0.46.3.dist-info/METADATA
cloudrift-0.46.3.dist-info/WHEEL
cloudrift-0.46.3.dist-info/top_level.txt
cloudrift-0.46.3.dist-info/RECORD
