Metadata-Version: 2.4
Name: cloudrift
Version: 0.46.3
Summary: A Python client for FairCompute API
Author-email: CloudRift Inc <inquiry@cloudrift.ai>
Project-URL: Homepage, https://cloudrift.ai
Project-URL: Issues, https://discord.gg/u8YZZJXdnr
Classifier: Programming Language :: Python :: 3
Classifier: License :: OSI Approved :: MIT License
Classifier: Operating System :: OS Independent
Requires-Python: >=3.8
License-File: LICENSE
Requires-Dist: requests[security]<3
Dynamic: license-file
